dufte/__init__.py
dufte/main.py
dufte/optimize.py
dufte-0.2.29.dist-info/LICENSE
dufte-0.2.29.dist-info/METADATA
dufte-0.2.29.dist-info/WHEEL
dufte-0.2.29.dist-info/top_level.txt
dufte-0.2.29.dist-info/RECORD
