Metadata-Version: 2.1
Name: dufte
Version: 0.2.29
Summary: Clean matplotlib plots
Home-page: https://github.com/nschloe/dufte
Author: Nico Schlömer
Author-email: nico.schloemer@gmail.com
License: MIT
Project-URL: Code, https://github.com/nschloe/dufte
Project-URL: Issues, https://github.com/nschloe/dufte/issues
Project-URL: Funding, https://github.com/sponsors/nschloe
Platform: UNKNOWN
Classifier: Development Status :: 4 - Beta
Classifier: Framework :: Matplotlib
Classifier: License :: OSI Approved :: MIT License
Classifier: Operating System :: OS Independent
Classifier: Programming Language :: Python
Classifier: Programming Language :: Python :: 3
Classifier: Programming Language :: Python :: 3.6
Classifier: Programming Language :: Python :: 3.7
Classifier: Programming Language :: Python :: 3.8
Classifier: Programming Language :: Python :: 3.9
Classifier: Programming Language :: Python :: 3.10
Classifier: Topic :: Utilities
Requires-Python: >=3.6
License-File: LICENSE
Requires-Dist: matplotlib
Requires-Dist: numpy
